pydantic_azure_secrets/__init__.py
pydantic_azure_secrets/azure_vault_settings.py
tests/__init__.py
tests/test_azure_vault_settings.py
pydantic_azure_secrets-0.1.0.dist-info/LICENSE
pydantic_azure_secrets-0.1.0.dist-info/METADATA
pydantic_azure_secrets-0.1.0.dist-info/WHEEL
pydantic_azure_secrets-0.1.0.dist-info/top_level.txt
pydantic_azure_secrets-0.1.0.dist-info/RECORD
