Metadata-Version: 2.1
Name: pydantic-azure-secrets
Version: 0.1.0
Summary: Pydantic extention to work with Azure Key Vaults
Home-page: https://github.com/kewtree1408/pydantic-azure-secrets
Author: Victoria
Author-email: me@vika.space
License: MIT
Platform: UNKNOWN
Classifier: Programming Language :: Python :: 3
Classifier: License :: OSI Approved :: MIT License
Classifier: Operating System :: OS Independent
Requires-Python: >=3.6
Requires-Dist: pydantic (==1.7.3)
Requires-Dist: python-dotenv (==0.15.0)
Requires-Dist: azure-identity (==1.5.0)
Requires-Dist: azure-keyvault-secrets (==4.2.0)
Provides-Extra: test
Requires-Dist: pytest (==6.2.1) ; extra == 'test'
Requires-Dist: pytest-cov (==2.11.1) ; extra == 'test'
Requires-Dist: black (==19.10b0) ; extra == 'test'
Requires-Dist: isort (==5.7.0) ; extra == 'test'
Requires-Dist: mypy (==0.800) ; extra == 'test'
Requires-Dist: mypy-extensions (==0.4.3) ; extra == 'test'
Requires-Dist: pylint (==2.6.0) ; extra == 'test'
Requires-Dist: flake8 (==3.8.4) ; extra == 'test'
